odoo/addons/stock_split_picking_dimension/README.rst
odoo/addons/stock_split_picking_dimension/__init__.py
odoo/addons/stock_split_picking_dimension/__manifest__.py
odoo/addons/stock_split_picking_dimension/exceptions.py
odoo/addons/stock_split_picking_dimension/i18n/it.po
odoo/addons/stock_split_picking_dimension/i18n/stock_split_picking_dimension.pot
odoo/addons/stock_split_picking_dimension/readme/CONTEXT.md
odoo/addons/stock_split_picking_dimension/readme/CONTRIBUTORS.md
odoo/addons/stock_split_picking_dimension/readme/CREDITS.md
odoo/addons/stock_split_picking_dimension/readme/DESCRIPTION.md
odoo/addons/stock_split_picking_dimension/readme/HISTORY.md
odoo/addons/stock_split_picking_dimension/readme/ROADMAP.md
odoo/addons/stock_split_picking_dimension/readme/USAGE.md
odoo/addons/stock_split_picking_dimension/static/description/icon.png
odoo/addons/stock_split_picking_dimension/static/description/index.html
odoo/addons/stock_split_picking_dimension/tests/__init__.py
odoo/addons/stock_split_picking_dimension/tests/test_stock_split_picking_dimension.py
odoo/addons/stock_split_picking_dimension/wizards/__init__.py
odoo/addons/stock_split_picking_dimension/wizards/stock_split_picking.py
odoo/addons/stock_split_picking_dimension/wizards/stock_split_picking.xml
odoo_addon_stock_split_picking_dimension-18.0.1.0.0.7.dist-info/METADATA
odoo_addon_stock_split_picking_dimension-18.0.1.0.0.7.dist-info/WHEEL
odoo_addon_stock_split_picking_dimension-18.0.1.0.0.7.dist-info/top_level.txt
odoo_addon_stock_split_picking_dimension-18.0.1.0.0.7.dist-info/RECORD
