Metadata-Version: 2.1
Name: odoo-addon-stock_split_picking_dimension
Version: 18.0.1.0.0.7
Requires-Python: >=3.10
Requires-Dist: odoo-addon-stock_picking_volume==18.0.*
Requires-Dist: odoo-addon-stock_split_picking==18.0.*
Requires-Dist: odoo==18.0.*
Summary: Split a picking in two not transferred pickings to ensure that the first one doesn't exceed given dimensions (nbr lines, volume, weight)
Home-page: https://github.com/OCA/stock-logistics-workflow
License: AGPL-3
Author: ACSONE SA/NV,Odoo Community Association (OCA)
Author-email: support@odoo-community.org
Classifier: Programming Language :: Python
Classifier: Framework :: Odoo
Classifier: Framework :: Odoo :: 18.0
Classifier: License :: OSI Approved :: GNU Affero General Public License v3
